grok_code.py
state.py
grokcode-1.3.0.dist-info/licenses/LICENSE
grokcode-1.3.0.dist-info/METADATA
grokcode-1.3.0.dist-info/WHEEL
grokcode-1.3.0.dist-info/entry_points.txt
grokcode-1.3.0.dist-info/top_level.txt
grokcode-1.3.0.dist-info/RECORD
