Metadata-Version: 2.4
Name: grokcode
Version: 1.3.0
Summary: An agentic CLI coding assistant powered by xAI Grok or OpenRouter
Author: GrokCode Contributors
License: MIT
Project-URL: Homepage, https://github.com/maximus242/grokcode
Project-URL: Documentation, https://github.com/maximus242/grokcode#readme
Project-URL: Repository, https://github.com/maximus242/grokcode
Project-URL: Issues, https://github.com/maximus242/grokcode/issues
Keywords: cli,ai,coding,assistant,grok,xai,openrouter,claude,agent
Classifier: Development Status :: 4 - Beta
Classifier: Environment :: Console
Classifier: Intended Audience :: Developers
Classifier: License :: OSI Approved :: MIT License
Classifier: Operating System :: OS Independent
Classifier: Programming Language :: Python :: 3
Classifier: Programming Language :: Python :: 3.10
Classifier: Programming Language :: Python :: 3.11
Classifier: Programming Language :: Python :: 3.12
Classifier: Programming Language :: Python :: 3.13
Classifier: Topic :: Software Development
Classifier: Topic :: Software Development :: Code Generators
Requires-Python: >=3.10
License-File: LICENSE
Requires-Dist: openai>=1.0.0
Requires-Dist: rich>=13.0.0
Requires-Dist: prompt-toolkit>=3.0.0
Requires-Dist: keyring>=24.0.0
Provides-Extra: dev
Requires-Dist: pytest>=7.0.0; extra == "dev"
Requires-Dist: pytest-asyncio>=0.21.0; extra == "dev"
Requires-Dist: pytest-mock>=3.10.0; extra == "dev"
Dynamic: license-file
